Metadata-Version: 1.0
Name: dictogc
Version: 0.0.7
Summary: sync dipendentincloud.it timesheet with google calendar
Home-page: https://bitbucket.org/submax82/dictogc/src/master/
Author: massimo
Author-email: massimo.cavalleri@gmail.com
License: GPL
Platform: UNKNOWN
